maimai_utils/__init__.py
maimai_utils/calculator.py
maimai_utils/data/song_data.json
maimai_utils/entity/__init__.py
maimai_utils/entity/chartsEntity.py
maimai_utils/entity/musciDetailEntity.py
maimai_utils/entity/scoresEntity.py
maimai_utils/query.py
maimai_utils-0.1.40.dist-info/LICENSE
maimai_utils-0.1.40.dist-info/METADATA
maimai_utils-0.1.40.dist-info/WHEEL
maimai_utils-0.1.40.dist-info/RECORD
