Metadata-Version: 2.1
Name: maimai-utils
Version: 0.1.40
Summary: `maimai-utils`是使用SEGA所属的街机音游maimai的数据进行开发的Python模块，用于快速查询游戏相关的数据。
License: MIT
Author: Kyoku
Author-email: hf4develop@163.com
Requires-Python: >=3.10,<4.0
Classifier: License :: OSI Approved :: MIT License
Classifier: Programming Language :: Python :: 3
Classifier: Programming Language :: Python :: 3.10
Classifier: Programming Language :: Python :: 3.11
Classifier: Programming Language :: Python :: 3.12
